setup.py
Statistic_Project_2023/TemperatureModel.py
Statistic_Project_2023/__init__.py
Statistic_Project_2023.egg-info/PKG-INFO
Statistic_Project_2023.egg-info/SOURCES.txt
Statistic_Project_2023.egg-info/dependency_links.txt
Statistic_Project_2023.egg-info/requires.txt
Statistic_Project_2023.egg-info/top_level.txt